rrpc.py
rrpc-0.0.2.dist-info/DESCRIPTION.rst
rrpc-0.0.2.dist-info/METADATA
rrpc-0.0.2.dist-info/RECORD
rrpc-0.0.2.dist-info/WHEEL
rrpc-0.0.2.dist-info/metadata.json
rrpc-0.0.2.dist-info/top_level.txt
